tests/__init__.py
tests/test_FilterLexer.py
tests/test_FilterParser.py
tests/test_TreeBuilder.py
tests/test_cross.py
tests/test_expand.py
treebuilder/FilterLexer.py
treebuilder/FilterParser.py
treebuilder/TreeBuilder.py
treebuilder/__init__.py
treebuilder/constants.py
treebuilder/cross.py
treebuilder/expand.py
treebuilder/json.py
treebuilder/nest.py
treebuilder/xml.py
treebuilder-0.13.dist-info/LICENSE
treebuilder-0.13.dist-info/METADATA
treebuilder-0.13.dist-info/WHEEL
treebuilder-0.13.dist-info/top_level.txt
treebuilder-0.13.dist-info/RECORD
