Metadata-Version: 2.1
Name: treebuilder
Version: 0.13
Summary: Build tree data model.
Home-page: https://github.com/fdieulle/treebuilder
Author: Fabien Dieulle
Author-email: fabiendieulle@hotmail.fr
License: UNKNOWN
Platform: UNKNOWN
Classifier: License :: OSI Approved :: MIT License
Classifier: Operating System :: OS Independent
Classifier: Programming Language :: Python :: 3.6
Classifier: Programming Language :: Python :: 3.7
Classifier: Programming Language :: Python :: 3.8
Classifier: Programming Language :: Python :: 3.9
Requires-Dist: sly
